README.md
setup.py
FunXXX/__init__.py
FunXXX/utils.py
FunXXX.egg-info/PKG-INFO
FunXXX.egg-info/SOURCES.txt
FunXXX.egg-info/dependency_links.txt
FunXXX.egg-info/top_level.txt