Metadata-Version: 2.1
Name: FunXXX
Version: 0.0.5
Summary: just a xxx tool
Home-page: https://github.com/hzfei
Author: hzfei
Author-email: 1027551108@qq.com
License: UNKNOWN
Platform: UNKNOWN
Classifier: Programming Language :: Python :: 3
Classifier: License :: OSI Approved :: MIT License
Classifier: Operating System :: OS Independent
